pydnp3.cpython-35m-x86_64-linux-gnu.so
pydnp3-0.1.0.dist-info/LICENSE.txt
pydnp3-0.1.0.dist-info/METADATA
pydnp3-0.1.0.dist-info/RECORD
pydnp3-0.1.0.dist-info/WHEEL
pydnp3-0.1.0.dist-info/top_level.txt
