Metadata-Version: 2.0
Name: pydnp3
Version: 0.1.0
Summary: pydnp3 -- python binding for opendnp3
Home-page: http://github.com/Kisensum/pydnp3
Author: Anh Nguyen
Author-email: anh@kisensum.com
License: Apache 2.0
Platform: macosx
Platform: linux
Classifier: Development Status :: 5 - Production/Stable
Classifier: License :: OSI Approved :: Apache Software License
Classifier: Programming Language :: Python
Classifier: Programming Language :: Python :: 2
Classifier: Programming Language :: Python :: 2.7
Classifier: Programming Language :: Python :: 3
Classifier: Programming Language :: Python :: 3.5
Classifier: Programming Language :: Python :: 3.6
Requires-Dist: pybind11 (>=2.2)
